pcas/__init__.py
pcas/_certificate.py
pcas/keyvalue/__init__.py
pcas/keyvalue/_condition_pb2.py
pcas/keyvalue/_condition_pb2_grpc.py
pcas/keyvalue/_connection.py
pcas/keyvalue/_convert.py
pcas/keyvalue/_kvdb_pb2.py
pcas/keyvalue/_kvdb_pb2_grpc.py
pcas/keyvalue/_sort_pb2.py
pcas/keyvalue/_sort_pb2_grpc.py
pcas/keyvalue/_table.py
pcas/keyvalue/_util.py
pcas/keyvalue/_value_pb2.py
pcas/keyvalue/_value_pb2_grpc.py
pcas/keyvalue/exceptions.py
pcas/keyvalue/record/__init__.py
pcas/keyvalue/record/_record.py
pcas/keyvalue/tests/__init__.py
pcas/keyvalue/tests/integration_test.py
pcas/logger/__init__.py
pcas/logger/_logd_pb2.py
pcas/logger/_logd_pb2_grpc.py
pcas/logger/_logger.py
pcas/logger/exceptions.py
pcas/sql/__init__.py
pcas/sql/_lexer.py
pcas/sql/_parser.py
pcas/sql/_scanner.py
pcas/sql/condition.py
pcas/sql/exceptions.py
pcas/sql/sort.py
pcas/sql/tests/__init__.py
pcas/sql/tests/lexer_test.py
pcas/sql/tests/parser_test.py
pcas/sql/tests/scanner_test.py
pcas-0.0.6.dist-info/AUTHORS.txt
pcas-0.0.6.dist-info/COPYING.txt
pcas-0.0.6.dist-info/METADATA
pcas-0.0.6.dist-info/WHEEL
pcas-0.0.6.dist-info/top_level.txt
pcas-0.0.6.dist-info/RECORD
