Metadata-Version: 2.1
Name: pcas
Version: 0.0.6
Summary: pcas provides an interface to PCAS microservices.
Home-page: https://bitbucket.org/pcas/python-interface
Author: Tom Coates, Alexander Kasprzyk
Author-email: t.coates@imperial.ac.uk
License: CC0
Platform: UNKNOWN
Classifier: Development Status :: 4 - Beta
Classifier: License :: CC0 1.0 Universal (CC0 1.0) Public Domain Dedication
Classifier: Programming Language :: Python
Classifier: Programming Language :: Python :: 3.8
Classifier: Programming Language :: Python :: 3.9
Classifier: Topic :: Software Development :: Libraries
Classifier: Topic :: Software Development :: Libraries :: Python Modules
Classifier: Intended Audience :: Developers
Classifier: Topic :: Scientific/Engineering :: Mathematics
Classifier: Topic :: Database :: Front-Ends
Classifier: Topic :: System :: Logging
Classifier: Programming Language :: SQL
Requires-Python: >=3.8
License-File: COPYING.txt
License-File: AUTHORS.txt
Requires-Dist: grpcio
Requires-Dist: protobuf
